robosystems_client/__init__.py
robosystems_client/client.py
robosystems_client/errors.py
robosystems_client/py.typed
robosystems_client/sdk-config.yaml
robosystems_client/types.py
robosystems_client/api/__init__.py
robosystems_client/api/agent/__init__.py
robosystems_client/api/agent/query_financial_agent.py
robosystems_client/api/auth/__init__.py
robosystems_client/api/auth/check_password_strength.py
robosystems_client/api/auth/complete_sso_auth.py
robosystems_client/api/auth/generate_sso_token.py
robosystems_client/api/auth/get_captcha_config.py
robosystems_client/api/auth/get_current_auth_user.py
robosystems_client/api/auth/get_password_policy.py
robosystems_client/api/auth/login_user.py
robosystems_client/api/auth/logout_user.py
robosystems_client/api/auth/refresh_session.py
robosystems_client/api/auth/register_user.py
robosystems_client/api/auth/sso_login.py
robosystems_client/api/auth/sso_token_exchange.py
robosystems_client/api/backup/__init__.py
robosystems_client/api/backup/create_backup.py
robosystems_client/api/backup/export_backup.py
robosystems_client/api/backup/get_backup_download_url.py
robosystems_client/api/backup/get_backup_stats.py
robosystems_client/api/backup/kuzu_backup_health.py
robosystems_client/api/backup/list_backups.py
robosystems_client/api/backup/restore_backup.py
robosystems_client/api/billing/__init__.py
robosystems_client/api/billing/get_available_subscription_plans_v1_graph_id_billing_available_plans_get.py
robosystems_client/api/billing/get_credit_billing_info_v1_graph_id_billing_credits_get.py
robosystems_client/api/billing/get_current_graph_bill.py
robosystems_client/api/billing/get_graph_billing_history.py
robosystems_client/api/billing/get_graph_monthly_bill.py
robosystems_client/api/billing/get_graph_pricing_info_v1_graph_id_billing_pricing_get.py
robosystems_client/api/billing/get_graph_subscription_v1_graph_id_billing_subscription_get.py
robosystems_client/api/billing/get_graph_usage_details.py
robosystems_sdk-0.1.8.dist-info/METADATA
robosystems_sdk-0.1.8.dist-info/WHEEL
robosystems_sdk-0.1.8.dist-info/RECORD
